setup.py
pyhelloworld3/__init__.py
pyhelloworld3/helloworld.py
pyhelloworld3.egg-info/PKG-INFO
pyhelloworld3.egg-info/SOURCES.txt
pyhelloworld3.egg-info/dependency_links.txt
pyhelloworld3.egg-info/pbr.json
pyhelloworld3.egg-info/top_level.txt