Metadata-Version: 1.1
Name: pyhelloworld3
Version: 1.0.0
Summary: Hello world
Home-page: https://github.com/rmkraus/pyhelloworld3/
Author: Ryan Kraus
Author-email: automicus@gmail.com
License: Apache Software License
Platform: any
Classifier: Programming Language :: Python
Classifier: Development Status :: 4 - Beta
Classifier: Natural Language :: English
Classifier: Environment :: Web Environment
Classifier: Intended Audience :: Developers
Classifier: License :: OSI Approved :: Apache Software License
Classifier: Operating System :: OS Independent
Classifier: Topic :: Software Development :: Libraries :: Python Modules
